objectlist/__init__.py
objectlist/base.py
objectlist-1.0.2.dist-info/LICENSE
objectlist-1.0.2.dist-info/METADATA
objectlist-1.0.2.dist-info/WHEEL
objectlist-1.0.2.dist-info/top_level.txt
objectlist-1.0.2.dist-info/RECORD
