Metadata-Version: 2.1
Name: objectlist
Version: 1.0.2
Summary: Use methods and method chaining on lists of objects.
Author-email: Ivo Severins <i.w.h.severins@tudelft.nl>
Project-URL: Homepage, https://github.com/ivoseverins/objectlist
Keywords: object,list,method,chaining
Classifier: Programming Language :: Python
Classifier: Programming Language :: Python :: 3
Classifier: License :: OSI Approved :: GNU General Public License v3 (GPLv3)
Requires-Python: >=3.9
License-File: LICENSE
Requires-Dist: numpy >=1.22
Requires-Dist: joblib
Requires-Dist: tqdm
Provides-Extra: dev
Requires-Dist: pytest ; extra == 'dev'
Requires-Dist: build ; extra == 'dev'
Requires-Dist: twine ; extra == 'dev'
